neuralop/__init__.py
neuralop/utils.py
neuralop/data/__init__.py
neuralop/data/datasets/__init__.py
neuralop/data/datasets/burgers.py
neuralop/data/datasets/car_cfd_dataset.py
neuralop/data/datasets/darcy.py
neuralop/data/datasets/dict_dataset.py
neuralop/data/datasets/hdf5_dataset.py
neuralop/data/datasets/mesh_datamodule.py
neuralop/data/datasets/navier_stokes.py
neuralop/data/datasets/nonlinear_poisson.py
neuralop/data/datasets/pt_dataset.py
neuralop/data/datasets/spherical_swe.py
neuralop/data/datasets/tensor_dataset.py
neuralop/data/datasets/the_well_dataset.py
neuralop/data/datasets/web_utils.py
neuralop/data/datasets/zarr_dataset.py
neuralop/data/datasets/tests/__init__.py
neuralop/data/datasets/tests/test_ptdatasets.py
neuralop/data/transforms/__init__.py
neuralop/data/transforms/base_transforms.py
neuralop/data/transforms/data_processors.py
neuralop/data/transforms/normalizers.py
neuralop/data/transforms/patching_transforms.py
neuralop/data/transforms/the_well_data_processors.py
neuralop/data/transforms/tests/__init__.py
neuralop/data/transforms/tests/test_data_processor.py
neuralop/data/transforms/tests/test_unit_gaussian_normalizer.py
neuralop/layers/__init__.py
neuralop/layers/attention_kernel_integral.py
neuralop/layers/base_spectral_conv.py
neuralop/layers/channel_mlp.py
neuralop/layers/coda_layer.py
neuralop/layers/complex.py
neuralop/layers/differential_conv.py
neuralop/layers/discrete_continuous_convolution.py
neuralop/layers/einsum_utils.py
neuralop/layers/embeddings.py
neuralop/layers/fno_block.py
neuralop/layers/fourier_continuation.py
neuralop/layers/gno_block.py
neuralop/layers/gno_weighting_functions.py
neuralop/layers/integral_transform.py
neuralop/layers/legacy_spectral_convolution.py
neuralop/layers/local_no_block.py
neuralop/layers/neighbor_search.py
neuralop/layers/normalization_layers.py
neuralop/layers/padding.py
neuralop/layers/resample.py
neuralop/layers/segment_csr.py
neuralop/layers/skip_connections.py
neuraloperator-2.0.0.dist-info/licenses/LICENSE
neuraloperator-2.0.0.dist-info/METADATA
neuraloperator-2.0.0.dist-info/WHEEL
neuraloperator-2.0.0.dist-info/top_level.txt
neuraloperator-2.0.0.dist-info/RECORD
