Metadata-Version: 2.4
Name: neuraloperator
Version: 2.0.0
Summary: NeuralOperator: Learning in Infinite Dimensions
Author-email: "Jean Kossaifi <jean.kossaifi@gmail.com>, David Pitt <david.h.pitt@gmail.com>, Nik Kovachki, Zongyi Li" <david.h.pitt@gmail.com>
License: MIT
Requires-Python: >=3.9
License-File: LICENSE
Requires-Dist: wandb
Requires-Dist: ruamel-yaml
Requires-Dist: zencfg
Requires-Dist: configmypy
Requires-Dist: tensorly
Requires-Dist: tensorly-torch
Requires-Dist: matplotlib
Requires-Dist: numpy>=1.25
Requires-Dist: opt-einsum
Requires-Dist: h5py
Requires-Dist: zencfg>=0.3.0
Provides-Extra: dev
Requires-Dist: pytest; extra == "dev"
Requires-Dist: flaky; extra == "dev"
Requires-Dist: black; extra == "dev"
Provides-Extra: doc
Requires-Dist: matplotlib; extra == "doc"
Requires-Dist: myst-nb; extra == "doc"
Requires-Dist: numpydoc; extra == "doc"
Requires-Dist: numpy>=1.25; extra == "doc"
Requires-Dist: sphinx; extra == "doc"
Requires-Dist: sphinx-gallery; extra == "doc"
Requires-Dist: sphinx-design; extra == "doc"
Requires-Dist: tensorly_sphinx_theme; extra == "doc"
Requires-Dist: torchtnt; extra == "doc"
Requires-Dist: torch_harmonics==0.7.4; extra == "doc"
Provides-Extra: all
Requires-Dist: pytest; extra == "all"
Requires-Dist: flaky; extra == "all"
Requires-Dist: black; extra == "all"
Requires-Dist: matplotlib; extra == "all"
Requires-Dist: myst-nb; extra == "all"
Requires-Dist: numpydoc; extra == "all"
Requires-Dist: sphinx; extra == "all"
Requires-Dist: sphinx-gallery; extra == "all"
Requires-Dist: sphinx-design; extra == "all"
Requires-Dist: tensorly_sphinx_theme; extra == "all"
Requires-Dist: torchtnt; extra == "all"
Requires-Dist: numpy>=1.25; extra == "all"
Requires-Dist: scipy; extra == "all"
Requires-Dist: torch_harmonics==0.7.4; extra == "all"
Dynamic: license-file
